qore-0.1.0.dist-info/METADATA
qore-0.1.0.dist-info/WHEEL
qore/encoder.py
qore/lib.pyi
qore/__init__.py
qore/lib.cpython-312-x86_64-linux-gnu.so
qore-0.1.0.dist-info/RECORD
